<?xml version="1.0" encoding="UTF-8"?>

<Root>
  <TreeNode Title="C06F1/00 火柴的机械加工" Target="frmContent" Href="../searchservlet?query=C06F1/00&amp;ipcsch=1&amp;db=all&amp;fuzzyipc=0&amp;pageSize=20&amp;currPage=1&amp;recordtotal=100&amp;singledb=null&amp;sIPC=null" CheckData="C06F1/00">
    <TreeNode Title="C06F1/02 #火柴梗的切割" Target="frmContent" Href="../searchservlet?query=C06F1/02&amp;ipcsch=1&amp;db=all&amp;fuzzyipc=0&amp;pageSize=20&amp;currPage=1&amp;recordtotal=100&amp;singledb=null&amp;sIPC=null" CheckData="C06F1/02"/>
    <TreeNode Title="C06F1/04 #在链板上充填火柴梗；卸火柴梗" Target="frmContent" Href="../searchservlet?query=C06F1/04&amp;ipcsch=1&amp;db=all&amp;fuzzyipc=0&amp;pageSize=20&amp;currPage=1&amp;recordtotal=100&amp;singledb=null&amp;sIPC=null" CheckData="C06F1/04"/>
    <TreeNode Title="C06F1/06 #火柴的浸沾、涂敷、浸渍或干燥的方法[2]" Target="frmContent" Href="../searchservlet?query=C06F1/06&amp;ipcsch=1&amp;db=all&amp;fuzzyipc=0&amp;pageSize=20&amp;currPage=1&amp;recordtotal=100&amp;singledb=null&amp;sIPC=null" CheckData="C06F1/06"/>
    <TreeNode Title="C06F1/08 #链板" Target="frmContent" Href="../searchservlet?query=C06F1/08&amp;ipcsch=1&amp;db=all&amp;fuzzyipc=0&amp;pageSize=20&amp;currPage=1&amp;recordtotal=100&amp;singledb=null&amp;sIPC=null" CheckData="C06F1/08">
      <TreeNode Title="C06F1/10 ##链板导向装置" Target="frmContent" Href="../searchservlet?query=C06F1/10&amp;ipcsch=1&amp;db=all&amp;fuzzyipc=0&amp;pageSize=20&amp;currPage=1&amp;recordtotal=100&amp;singledb=null&amp;sIPC=null" CheckData="C06F1/10"/>
    </TreeNode>
    <TreeNode Title="C06F1/12 #火柴的装盒" Target="frmContent" Href="../searchservlet?query=C06F1/12&amp;ipcsch=1&amp;db=all&amp;fuzzyipc=0&amp;pageSize=20&amp;currPage=1&amp;recordtotal=100&amp;singledb=null&amp;sIPC=null" CheckData="C06F1/12"/>
    <TreeNode Title="C06F1/14 #擦火片的生产" Target="frmContent" Href="../searchservlet?query=C06F1/14&amp;ipcsch=1&amp;db=all&amp;fuzzyipc=0&amp;pageSize=20&amp;currPage=1&amp;recordtotal=100&amp;singledb=null&amp;sIPC=null" CheckData="C06F1/14"/>
    <TreeNode Title="C06F1/16 #互相连接的(如成条的或成片的)火柴生产" Target="frmContent" Href="../searchservlet?query=C06F1/16&amp;ipcsch=1&amp;db=all&amp;fuzzyipc=0&amp;pageSize=20&amp;currPage=1&amp;recordtotal=100&amp;singledb=null&amp;sIPC=null" CheckData="C06F1/16"/>
    <TreeNode Title="C06F1/18 #与火柴生产过程相结合的火柴或火柴盒上的印刷" Target="frmContent" Href="../searchservlet?query=C06F1/18&amp;ipcsch=1&amp;db=all&amp;fuzzyipc=0&amp;pageSize=20&amp;currPage=1&amp;recordtotal=100&amp;singledb=null&amp;sIPC=null" CheckData="C06F1/18"/>
    <TreeNode Title="C06F1/20 #擦火面层的涂敷，如在火柴盒、在火柴簿上" Target="frmContent" Href="../searchservlet?query=C06F1/20&amp;ipcsch=1&amp;db=all&amp;fuzzyipc=0&amp;pageSize=20&amp;currPage=1&amp;recordtotal=100&amp;singledb=null&amp;sIPC=null" CheckData="C06F1/20"/>
    <TreeNode Title="C06F1/22 #火柴的集装" Target="frmContent" Href="../searchservlet?query=C06F1/22&amp;ipcsch=1&amp;db=all&amp;fuzzyipc=0&amp;pageSize=20&amp;currPage=1&amp;recordtotal=100&amp;singledb=null&amp;sIPC=null" CheckData="C06F1/22"/>
    <TreeNode Title="C06F1/24 #防火安全装置" Target="frmContent" Href="../searchservlet?query=C06F1/24&amp;ipcsch=1&amp;db=all&amp;fuzzyipc=0&amp;pageSize=20&amp;currPage=1&amp;recordtotal=100&amp;singledb=null&amp;sIPC=null" CheckData="C06F1/24"/>
    <TreeNode Title="C06F1/26 #火柴生产全过程用机器" Target="frmContent" Href="../searchservlet?query=C06F1/26&amp;ipcsch=1&amp;db=all&amp;fuzzyipc=0&amp;pageSize=20&amp;currPage=1&amp;recordtotal=100&amp;singledb=null&amp;sIPC=null" CheckData="C06F1/26"/>
  </TreeNode>
  <TreeNode Title="C06F3/00 火柴生产的化学部分" Target="frmContent" Href="../searchservlet?query=C06F3/00&amp;ipcsch=1&amp;db=all&amp;fuzzyipc=0&amp;pageSize=20&amp;currPage=1&amp;recordtotal=100&amp;singledb=null&amp;sIPC=null" CheckData="C06F3/00">
    <TreeNode Title="C06F3/02 #火柴用木片或其代用品" Target="frmContent" Href="../searchservlet?query=C06F3/02&amp;ipcsch=1&amp;db=all&amp;fuzzyipc=0&amp;pageSize=20&amp;currPage=1&amp;recordtotal=100&amp;singledb=null&amp;sIPC=null" CheckData="C06F3/02">
      <TreeNode Title="C06F3/04 ##在浸沾前后的化学处理，如染色、浸渍" Target="frmContent" Href="../searchservlet?query=C06F3/04&amp;ipcsch=1&amp;db=all&amp;fuzzyipc=0&amp;pageSize=20&amp;currPage=1&amp;recordtotal=100&amp;singledb=null&amp;sIPC=null" CheckData="C06F3/04"/>
    </TreeNode>
    <TreeNode Title="C06F3/08 #擦火面层药剂" Target="frmContent" Href="../searchservlet?query=C06F3/08&amp;ipcsch=1&amp;db=all&amp;fuzzyipc=0&amp;pageSize=20&amp;currPage=1&amp;recordtotal=100&amp;singledb=null&amp;sIPC=null" CheckData="C06F3/08"/>
  </TreeNode>
  <TreeNode Title="C06F5/00 火柴(火柴簿入A24F 27/12)" Target="frmContent" Href="../searchservlet?query=C06F5/00&amp;ipcsch=1&amp;db=all&amp;fuzzyipc=0&amp;pageSize=20&amp;currPage=1&amp;recordtotal=100&amp;singledb=null&amp;sIPC=null" CheckData="C06F5/00">
    <TreeNode Title="C06F5/02 #永久火柴" Target="frmContent" Href="../searchservlet?query=C06F5/02&amp;ipcsch=1&amp;db=all&amp;fuzzyipc=0&amp;pageSize=20&amp;currPage=1&amp;recordtotal=100&amp;singledb=null&amp;sIPC=null" CheckData="C06F5/02"/>
    <TreeNode Title="C06F5/04 #蜡火柴C07" Target="frmContent" Href="../searchservlet?query=C06F5/04&amp;ipcsch=1&amp;db=all&amp;fuzzyipc=0&amp;pageSize=20&amp;currPage=1&amp;recordtotal=100&amp;singledb=null&amp;sIPC=null" CheckData="C06F5/04"/>
  </TreeNode>
</Root>
